sh3dkit/__init__.py
sh3dkit/bin/__init__.py
sh3dkit/bin/sh3d2svg.py
sh3dkit/renderer/HomeRenderer.py
sh3dkit/renderer/SvgHomeRenderer.py
sh3dkit/renderer/__init__.py
sh3dkit-0.3.0.dist-info/licenses/LICENSE
sh3dkit-0.3.0.dist-info/METADATA
sh3dkit-0.3.0.dist-info/WHEEL
sh3dkit-0.3.0.dist-info/entry_points.txt
sh3dkit-0.3.0.dist-info/top_level.txt
sh3dkit-0.3.0.dist-info/RECORD
